{
  "updatedAt": "2026-06-02T09:19:01.217Z",
  "totalCommits": 2267,
  "languages": [
    {
      "name": "JavaScript",
      "percentage": "28.9"
    },
    {
      "name": "CSS",
      "percentage": "19.9"
    },
    {
      "name": "Astro",
      "percentage": "18.5"
    },
    {
      "name": "HTML",
      "percentage": "9.2"
    },
    {
      "name": "TypeScript",
      "percentage": "7.0"
    },
    {
      "name": "Shell",
      "percentage": "6.1"
    },
    {
      "name": "Stylus",
      "percentage": "5.7"
    },
    {
      "name": "SCSS",
      "percentage": "4.7"
    }
  ]
}